Workbook

Sheet Cover
A1: PROJECT 4 — UK TAX COMPUTATION
A3: Individual & Company Tax Computation
A5: Tax year | B5: 2026/27
A6: Individual case | B6: Alex Morgan — Self-employed Business Consultant
A7: Company case | B7: NorthPeak Outdoor Equipment Ltd — UK private limited company
A8: Software | B8: Microsoft Excel
A9: Status | B9: Day 1 — Workbook setup and source data
A12: Project objective
A13: Prepare professional UK individual and company tax computations by reconciling accounting profit to taxable profit, identifying tax adjustments, applying capital allowances and documenting the calculation clearly.
A16: Disclaimer:
A17: This project uses fictional data for educational and portfolio purposes only. Tax rates and thresholds are based on the stated tax year and should be checked against current HMRC guidance before use for any real tax filing or advisory purpose.

Sheet Tax Rates
A1: UK TAX RATES — 2026/27
A2: Item | B2: Rate / Limit | C2: Use in project | D2: Source
A3: Personal Allowance | B3: 12570 | C3: Individual tax computation | D3: HMRC
A4: Basic rate | B4: 0.2 | C4: Taxable income up to £37,700 | D4: HMRC
A5: Basic rate limit | B5: 37700 | C5: Taxable income band | D5: HMRC
A6: Higher rate | B6: 0.4 | C6: Taxable income £37,701–£125,140 | D6: HMRC
A7: Additional rate | B7: 0.45 | C7: Taxable income above £125,140 | D7: HMRC
A8: Personal Allowance taper starts | B8: 100000 | C8: Allowance reduces above this income | D8: HMRC
A9: Corporation Tax small profits rate | B9: 0.19 | C9: Profits under £50,000 | D9: HMRC
A10: Corporation Tax main rate | B10: 0.25 | C10: Profits over £250,000 | D10: HMRC
A11: CT marginal relief lower limit | B11: 50000 | C11: Lower limit | D11: HMRC
A12: CT marginal relief upper limit | B12: 250000 | C12: Upper limit | D12: HMRC
A13: CT standard fraction | B13: 0.015 | C13: 3/200 marginal relief fraction | D13: HMRC
A14: Annual Investment Allowance | B14: 1000000 | C14: Maximum AIA amount | D14: HMRC

Sheet Individual Source Data
A1: INDIVIDUAL SOURCE DATA
A2: Client | B2: Alex Morgan
A3: Business | B3: Morgan Business Consulting
A4: Tax year | B4: 2026/27
A6: Item | B6: Amount (£) | C6: Treatment / note | D6: Tax adjustment
A7: Net profit per accounts | B7: 78400 | C7: Starting accounting profit | D7: Starting point
A8: Depreciation | B8: 6200 | C8: Accounting depreciation | D8: Add back
A9: Client entertaining | B9: 1500 | C9: Disallowable for tax | D9: Add back
A10: Fines / penalties | B10: 450 | C10: Disallowable | D10: Add back
A11: Personal expense in business costs | B11: 1250 | C11: Not incurred wholly for trade | D11: Add back
A12: Qualifying equipment purchased | B12: 8000 | C12: Qualifying plant and machinery | D12: Capital expenditure
A13: Annual Investment Allowance claimed | B13: 8000 | C13: Assumed fully qualifying | D13: Deduct

Sheet Individual Tax Comp
A1: INDIVIDUAL TAX COMPUTATION — 2026/27
A3: Net profit per accounts | B3: ='Individual Source Data'!B7 -> 78400
A4: Add: depreciation | B4: ='Individual Source Data'!B8 -> 6200
A5: Add: client entertaining | B5: ='Individual Source Data'!B9 -> 1500
A6: Add: fines / penalties | B6: ='Individual Source Data'!B10 -> 450
A7: Add: personal expense | B7: ='Individual Source Data'!B11 -> 1250
A8: Less: capital allowances / AIA | B8: =-'Individual Source Data'!B13 -> -8000
A9: Adjusted trading profit | B9: =SUM(B3:B8) -> 79800
A10: Less: Personal Allowance | B10: =-'Tax Rates'!B3 -> -12570
A11: Taxable income | B11: =SUM(B9:B10) -> 67230
A13: Income tax laibility | B13: £
A14: Taxable non-savings income | B14: 67230
A15: Basic-rate band | B15: 37700
A16: Tax at 20% | B16: =B15*20% -> 7540
A17: Higher-rate income | B17: 29530
A18: Tax at 40% | B18: =B17*40% -> 11812
A19: Income Tax Liability | B19: =B16+B18 -> 19352

Sheet Capital Allowances
A1: CAPITAL ALLOWANCES WORKING
A2: Asset | B2: Cost (£) | C2: Allowance | D2: Claim (£)
A3: Business equipment | B3: 8000 | C3: AIA 100% | D3: =B3 -> 8000
A5: Note | B5: AIA can provide a 100% deduction for qualifying plant and machinery, subject to the applicable rules.

Sheet Company Source Data
A1: COMPANY SOURCE DATA
A2: Company | B2: NorthPeak Outdoor Equipment Ltd
A3: Accounting period | B3: 1 Apr 2026 – 31 Mar 2027
A4: Business | B4: Sports & camping equipment retail
A6: Item | B6: Amount (£) | C6: Treatment / note | D6: Tax adjustment
A7: Profit before tax per accounts | B7: 210000 | C7: Starting accounting profit | D7: Starting point
A8: Depreciation | B8: 25000 | C8: Accounting depreciation | D8: Add back
A9: Client entertaining | B9: 4000 | C9: Disallowable | D9: Add back
A10: Legal fees relating to capital acquisition | B10: 3000 | C10: Capital expenditure | D10: Add back
A11: Qualifying equipment acquired | B11: 20000 | C11: Qualifying plant and machinery | D11: Capital expenditure
A12: Annual Investment Allowance claimed | B12: 20000 | C12: Assumed fully qualifying | D12: Deduct

Sheet Company Tax Comp
A1: COMPANY TAX COMPUTATION — FINANCIAL YEAR 2026
A3: Profit before tax per accounts | B3: ='Company Source Data'!B7 -> 210000
A4: Add: depreciation | B4: ='Company Source Data'!B8 -> 25000
A5: Add: client entertaining | B5: ='Company Source Data'!B9 -> 4000
A6: Add: capital legal fees | B6: ='Company Source Data'!B10 -> 3000
A7: Less: capital allowances / AIA | B7: =-'Company Source Data'!B12 -> -20000
A8: Taxable total profits | B8: =SUM(B3:B7) -> 222000
A9: Corporation Tax | B9: =B15 -> 55080
A11: Corporation tax liability | B11: £
A12: Taxable total profits | B12: 222000
A13: Corporation Tax at 25% | B13: =B12*25% -> 55500
A14: Less: Marginal Relief | B14: =-((250000-222000)*3/200) -> -420
A15: Corporation Tax liability | B15: 55080
A18: Assumption: NorthPeak Outdoor Equipment Ltd has no associated companies and no relevant exempt distributions/other adjustments affecting augmented profits.

Sheet Tax Reconciliation
A1: TAX RECONCILIATION
A4: Entity | B4: Accounting Profit (£) | C4: Tax Adjustments (£) | D4: Adjusted Trading Profit (£)
A5: Individual | B5: ='Individual Source Data'!B7 -> 78400 | C5: =D5-B5 -> 1400 | D5: =79800 -> 79800
A6: Company | B6: ='Company Source Data'!B7 -> 210000 | C6: =D6-B6 -> 12000 | D6: ='Company Tax Comp'!B8 -> 222000
A8: Purpose | B8: Reconcile accounting profit to taxable profit
